{
"nodes": [
{"id": "0", "group": 0}, 
{"id": "1", "group": 0}, 
{"id": "2", "group": 0}, 
{"id": "3", "group": 0}
], 
"links": [
{"source": "0", "target": "1", "value": 0.15764178791061517}, 
{"source": "0", "target": "2", "value": 0.13177929772858168}, 
{"source": "0", "target": "3", "value": 0.45327183607966964}, 
{"source": "1", "target": "0", "value": 0.15764178791061517}, 
{"source": "1", "target": "2", "value": 0.1710635972366426}, 
{"source": "1", "target": "3", "value": 0.5931920615916327}, 
{"source": "2", "target": "0", "value": 0.13177929772858168}, 
{"source": "2", "target": "1", "value": 0.1710635972366426}, 
{"source": "2", "target": "3", "value": 0.42836421910391426}, 
{"source": "3", "target": "0", "value": 0.45327183607966964}, 
{"source": "3", "target": "1", "value": 0.5931920615916327}, 
{"source": "3", "target": "2", "value": 0.42836421910391426}
], 
"health_score": [
{"id": 2.9802541140013004}
]
}
