{
"nodes": [
{"id": "0", "group": 0}, 
{"id": "1", "group": 0}, 
{"id": "2", "group": 0}
], 
"links": [
{"source": "0", "target": "1", "value": 0.12111542981119361}, 
{"source": "0", "target": "2", "value": 0.315374673069197}, 
{"source": "1", "target": "0", "value": 0.12111542981119361}, 
{"source": "1", "target": "2", "value": 0.23048194386420276}, 
{"source": "2", "target": "0", "value": 0.315374673069197}, 
{"source": "2", "target": "1", "value": 0.23048194386420276}
], 
"health_score": 0.6188725823527923
}