{
"nodes": [
{"id": "0", "group": 0}, 
{"id": "1", "group": 0}, 
{"id": "2", "group": 0}, 
{"id": "3", "group": 0}, 
{"id": "4", "group": 0}, 
{"id": "5", "group": 0}, 
{"id": "6", "group": 0}, 
{"id": "7", "group": 0}, 
{"id": "8", "group": 0}
], 
"links": [
{"source": "0", "target": "1", "value": 0.6621619731841978}, 
{"source": "0", "target": "2", "value": 0.20851424986246084}, 
{"source": "0", "target": "3", "value": 0.09463801468968436}, 
{"source": "0", "target": "4", "value": 0.6166767839918308}, 
{"source": "0", "target": "5", "value": 0.26408810746881994}, 
{"source": "0", "target": "6", "value": 0.38790219141467136}, 
{"source": "0", "target": "7", "value": 0.682931182904154}, 
{"source": "0", "target": "8", "value": 0.37403474620163957}, 
{"source": "1", "target": "0", "value": 0.6621619731841978}, 
{"source": "1", "target": "2", "value": 0.5664260607573575}, 
{"source": "1", "target": "3", "value": 0.6935159424898474}, 
{"source": "1", "target": "4", "value": 0.5035281510557863}, 
{"source": "1", "target": "5", "value": 0.4050272519961499}, 
{"source": "1", "target": "6", "value": 0.4758026666057323}, 
{"source": "1", "target": "7", "value": 0.1988176514130407}, 
{"source": "1", "target": "8", "value": 0.4625607928601398}, 
{"source": "2", "target": "0", "value": 0.20851424986246084}, 
{"source": "2", "target": "1", "value": 0.5664260607573575}, 
{"source": "2", "target": "3", "value": 0.29913649604063614}, 
{"source": "2", "target": "4", "value": 0.4092725318770027}, 
{"source": "2", "target": "5", "value": 0.2344152156707697}, 
{"source": "2", "target": "6", "value": 0.4500315884385791}, 
{"source": "2", "target": "7", "value": 0.5198307442074521}, 
{"source": "2", "target": "8", "value": 0.17499355473276523}, 
{"source": "3", "target": "0", "value": 0.09463801468968436}, 
{"source": "3", "target": "1", "value": 0.6935159424898474}, 
{"source": "3", "target": "2", "value": 0.29913649604063614}, 
{"source": "3", "target": "4", "value": 0.703599593148921}, 
{"source": "3", "target": "5", "value": 0.2886064133194235}, 
{"source": "3", "target": "6", "value": 0.36084871580967864}, 
{"source": "3", "target": "7", "value": 0.7438956090647352}, 
{"source": "3", "target": "8", "value": 0.45716976141339744}, 
{"source": "4", "target": "0", "value": 0.6166767839918308}, 
{"source": "4", "target": "1", "value": 0.5035281510557863}, 
{"source": "4", "target": "2", "value": 0.4092725318770027}, 
{"source": "4", "target": "3", "value": 0.703599593148921}, 
{"source": "4", "target": "5", "value": 0.518796457160416}, 
{"source": "4", "target": "6", "value": 0.7374452573434668}, 
{"source": "4", "target": "7", "value": 0.31973649077092414}, 
{"source": "4", "target": "8", "value": 0.24935085017901382}, 
{"source": "5", "target": "0", "value": 0.26408810746881994}, 
{"source": "5", "target": "1", "value": 0.4050272519961499}, 
{"source": "5", "target": "2", "value": 0.2344152156707697}, 
{"source": "5", "target": "3", "value": 0.2886064133194235}, 
{"source": "5", "target": "4", "value": 0.518796457160416}, 
{"source": "5", "target": "6", "value": 0.2000655911316799}, 
{"source": "5", "target": "7", "value": 0.4793386470200999}, 
{"source": "5", "target": "8", "value": 0.2817052598306257}, 
{"source": "6", "target": "0", "value": 0.38790219141467136}, 
{"source": "6", "target": "1", "value": 0.4758026666057323}, 
{"source": "6", "target": "2", "value": 0.4500315884385791}, 
{"source": "6", "target": "3", "value": 0.36084871580967864}, 
{"source": "6", "target": "4", "value": 0.7374452573434668}, 
{"source": "6", "target": "5", "value": 0.2000655911316799}, 
{"source": "6", "target": "7", "value": 0.6419697127013637}, 
{"source": "6", "target": "8", "value": 0.5141806781064305}, 
{"source": "7", "target": "0", "value": 0.682931182904154}, 
{"source": "7", "target": "1", "value": 0.1988176514130407}, 
{"source": "7", "target": "2", "value": 0.5198307442074521}, 
{"source": "7", "target": "3", "value": 0.7438956090647352}, 
{"source": "7", "target": "4", "value": 0.31973649077092414}, 
{"source": "7", "target": "5", "value": 0.4793386470200999}, 
{"source": "7", "target": "6", "value": 0.6419697127013637}, 
{"source": "7", "target": "8", "value": 0.35979832010294116}, 
{"source": "8", "target": "0", "value": 0.37403474620163957}, 
{"source": "8", "target": "1", "value": 0.4625607928601398}, 
{"source": "8", "target": "2", "value": 0.17499355473276523}, 
{"source": "8", "target": "3", "value": 0.45716976141339744}, 
{"source": "8", "target": "4", "value": 0.24935085017901382}, 
{"source": "8", "target": "5", "value": 0.2817052598306257}, 
{"source": "8", "target": "6", "value": 0.5141806781064305}, 
{"source": "8", "target": "7", "value": 0.35979832010294116}
], 
"health_score": 4.025155031160641
}