{
"nodes": [
{"id": "0", "group": 0}, 
{"id": "1", "group": 0}, 
{"id": "2", "group": 0}, 
{"id": "3", "group": 0}, 
{"id": "4", "group": 0}, 
{"id": "5", "group": 0}, 
{"id": "6", "group": 0}
], 
"links": [
{"source": "0", "target": "1", "value": 0.4913257487534557}, 
{"source": "0", "target": "2", "value": 0.34656981469333076}, 
{"source": "0", "target": "3", "value": 0.4884545930922366}, 
{"source": "0", "target": "4", "value": 0.2778406442426483}, 
{"source": "0", "target": "5", "value": 0.24303732948670342}, 
{"source": "0", "target": "6", "value": 0.23787400412847612}, 
{"source": "1", "target": "0", "value": 0.4913257487534557}, 
{"source": "1", "target": "2", "value": 0.7192990558625246}, 
{"source": "1", "target": "3", "value": 0.08694171368761341}, 
{"source": "1", "target": "4", "value": 0.2140845503244091}, 
{"source": "1", "target": "5", "value": 0.31286520310752686}, 
{"source": "1", "target": "6", "value": 0.3228696065671498}, 
{"source": "2", "target": "0", "value": 0.34656981469333076}, 
{"source": "2", "target": "1", "value": 0.7192990558625246}, 
{"source": "2", "target": "3", "value": 0.6769751263316086}, 
{"source": "2", "target": "4", "value": 0.5204011388864889}, 
{"source": "2", "target": "5", "value": 0.5491542817626904}, 
{"source": "2", "target": "6", "value": 0.39713826735363894}, 
{"source": "3", "target": "0", "value": 0.4884545930922366}, 
{"source": "3", "target": "1", "value": 0.08694171368761341}, 
{"source": "3", "target": "2", "value": 0.6769751263316086}, 
{"source": "3", "target": "4", "value": 0.21738140046286425}, 
{"source": "3", "target": "5", "value": 0.35150224926250434}, 
{"source": "3", "target": "6", "value": 0.2855111621313466}, 
{"source": "4", "target": "0", "value": 0.2778406442426483}, 
{"source": "4", "target": "1", "value": 0.2140845503244091}, 
{"source": "4", "target": "2", "value": 0.5204011388864889}, 
{"source": "4", "target": "3", "value": 0.21738140046286425}, 
{"source": "4", "target": "5", "value": 0.1578261487435428}, 
{"source": "4", "target": "6", "value": 0.11926399859832651}, 
{"source": "5", "target": "0", "value": 0.24303732948670342}, 
{"source": "5", "target": "1", "value": 0.31286520310752686}, 
{"source": "5", "target": "2", "value": 0.5491542817626904}, 
{"source": "5", "target": "3", "value": 0.35150224926250434}, 
{"source": "5", "target": "4", "value": 0.1578261487435428}, 
{"source": "5", "target": "6", "value": 0.24254675599384232}, 
{"source": "6", "target": "0", "value": 0.23787400412847612}, 
{"source": "6", "target": "1", "value": 0.3228696065671498}, 
{"source": "6", "target": "2", "value": 0.39713826735363894}, 
{"source": "6", "target": "3", "value": 0.2855111621313466}, 
{"source": "6", "target": "4", "value": 0.11926399859832651}, 
{"source": "6", "target": "5", "value": 0.24254675599384232}
], 
"health_score": 2.472776502323529
}