{
"nodes": [
{"id": "0", "group": 0}, 
{"id": "1", "group": 0}, 
{"id": "2", "group": 0}, 
{"id": "3", "group": 0}, 
{"id": "4", "group": 0}, 
{"id": "5", "group": 0}, 
{"id": "6", "group": 0}, 
{"id": "7", "group": 0}
], 
"links": [
{"source": "0", "target": "1", "value": 0.33729022685746857}, 
{"source": "0", "target": "2", "value": 0.3974391104603386}, 
{"source": "0", "target": "3", "value": 0.2313095586588397}, 
{"source": "0", "target": "4", "value": 0.06663597510346321}, 
{"source": "0", "target": "5", "value": 0.40525758731417943}, 
{"source": "0", "target": "6", "value": 0.127673283691343}, 
{"source": "0", "target": "7", "value": 0.4449569162558121}, 
{"source": "1", "target": "0", "value": 0.33729022685746857}, 
{"source": "1", "target": "2", "value": 0.42039717226680423}, 
{"source": "1", "target": "3", "value": 0.2520302572426836}, 
{"source": "1", "target": "4", "value": 0.3593807910497606}, 
{"source": "1", "target": "5", "value": 0.09491523176215526}, 
{"source": "1", "target": "6", "value": 0.4605899816663245}, 
{"source": "1", "target": "7", "value": 0.13301179535274846}, 
{"source": "2", "target": "0", "value": 0.3974391104603386}, 
{"source": "2", "target": "1", "value": 0.42039717226680423}, 
{"source": "2", "target": "3", "value": 0.1890325849451684}, 
{"source": "2", "target": "4", "value": 0.3585899854683265}, 
{"source": "2", "target": "5", "value": 0.5126413938356054}, 
{"source": "2", "target": "6", "value": 0.45439003628275954}, 
{"source": "2", "target": "7", "value": 0.3912464602628913}, 
{"source": "3", "target": "0", "value": 0.2313095586588397}, 
{"source": "3", "target": "1", "value": 0.2520302572426836}, 
{"source": "3", "target": "2", "value": 0.1890325849451684}, 
{"source": "3", "target": "4", "value": 0.21737675302196188}, 
{"source": "3", "target": "5", "value": 0.3468701023290062}, 
{"source": "3", "target": "6", "value": 0.32176092343427426}, 
{"source": "3", "target": "7", "value": 0.2868011510065167}, 
{"source": "4", "target": "0", "value": 0.06663597510346321}, 
{"source": "4", "target": "1", "value": 0.3593807910497606}, 
{"source": "4", "target": "2", "value": 0.3585899854683265}, 
{"source": "4", "target": "3", "value": 0.21737675302196188}, 
{"source": "4", "target": "5", "value": 0.4369986828922858}, 
{"source": "4", "target": "6", "value": 0.10858679937635796}, 
{"source": "4", "target": "7", "value": 0.4528156462432057}, 
{"source": "5", "target": "0", "value": 0.40525758731417943}, 
{"source": "5", "target": "1", "value": 0.09491523176215526}, 
{"source": "5", "target": "2", "value": 0.5126413938356054}, 
{"source": "5", "target": "3", "value": 0.3468701023290062}, 
{"source": "5", "target": "4", "value": 0.4369986828922858}, 
{"source": "5", "target": "6", "value": 0.5321314278496623}, 
{"source": "5", "target": "7", "value": 0.13160092672486484}, 
{"source": "6", "target": "0", "value": 0.127673283691343}, 
{"source": "6", "target": "1", "value": 0.4605899816663245}, 
{"source": "6", "target": "2", "value": 0.45439003628275954}, 
{"source": "6", "target": "3", "value": 0.32176092343427426}, 
{"source": "6", "target": "4", "value": 0.10858679937635796}, 
{"source": "6", "target": "5", "value": 0.5321314278496623}, 
{"source": "6", "target": "7", "value": 0.5598752058121128}, 
{"source": "7", "target": "0", "value": 0.4449569162558121}, 
{"source": "7", "target": "1", "value": 0.13301179535274846}, 
{"source": "7", "target": "2", "value": 0.3912464602628913}, 
{"source": "7", "target": "3", "value": 0.2868011510065167}, 
{"source": "7", "target": "4", "value": 0.4528156462432057}, 
{"source": "7", "target": "5", "value": 0.13160092672486484}, 
{"source": "7", "target": "6", "value": 0.5598752058121128}
], 
"health_score": 2.7462758026229928
}